polars_ab_utils-0.0.1.dist-info/METADATA
polars_ab_utils-0.0.1.dist-info/WHEEL
polars_ab_utils.libs/libgcc_s-1e52349c.so.1
polars_ab_utils/typing.py
polars_ab_utils/__init__.py
polars_ab_utils/_internal.abi3.so
polars_ab_utils-0.0.1.dist-info/RECORD
